colonizer
